firelab/__init__.py
firelab/__main__.py
firelab/base_trainer.py
firelab/cli.py
firelab/config.py
firelab/hpo.py
firelab/manager.py
firelab/utils/__init__.py
firelab/utils/data_utils.py
firelab/utils/distributed_utils.py
firelab/utils/fs_utils.py
firelab/utils/training_utils.py
firelab-0.0.26.dist-info/METADATA
firelab-0.0.26.dist-info/WHEEL
firelab-0.0.26.dist-info/entry_points.txt
firelab-0.0.26.dist-info/top_level.txt
firelab-0.0.26.dist-info/zip-safe
firelab-0.0.26.dist-info/RECORD
