Metadata-Version: 2.1
Name: firelab
Version: 0.0.26
Summary: An experimental framework to run pytorch experiments
Home-page: https://github.com/universome/firelab
Author: Ivan Skorokhodov
Author-email: iskorokhodov@gmail.com
License: BSD
Platform: UNKNOWN
Requires-Python: >=3.6
Requires-Dist: PyYAML (>=3.12)
Requires-Dist: torch (>=1.1.0)
Requires-Dist: tb-nightly (>=1.14.*)
Requires-Dist: future (>=0.17)
Requires-Dist: coloredlogs (>=10.0)
Requires-Dist: portalocker (>=2.0.0)
